survival_evaluation/__init__.py
survival_evaluation/evaluations.py
survival_evaluation/types.py
survival_evaluation/utility.py
survival_evaluation-0.1.3.dist-info/LICENSE
survival_evaluation-0.1.3.dist-info/WHEEL
survival_evaluation-0.1.3.dist-info/METADATA
survival_evaluation-0.1.3.dist-info/RECORD
