Metadata-Version: 2.1
Name: survival-evaluation
Version: 0.1.3
Summary: A couple survival evaluation metrics.
Home-page: https://github.com/haiderstats/survival_evaluation
License: MIT
Keywords: survival,evaluation
Author: Humza Haider
Author-email: humza@haiderstats.com
Requires-Python: >=3.6,<4.0
Classifier: License :: OSI Approved :: MIT License
Classifier: Programming Language :: Python :: 3
Classifier: Programming Language :: Python :: 3.6
Classifier: Programming Language :: Python :: 3.7
Classifier: Programming Language :: Python :: 3.8
Classifier: Programming Language :: Python :: 3.9
Requires-Dist: numpy (>=1.19.4,<2.0.0)
Requires-Dist: scipy (>=1.5.4,<2.0.0)
Project-URL: Documentation, https://github.com/haiderstats/survival_evaluation/blob/main/README.md
Project-URL: Repository, https://github.com/haiderstats/survival_evaluation
